nibe_mqtt/__init__.py
nibe_mqtt/config.py
nibe_mqtt/mqtt.py
nibe_mqtt/service.py
nibe_mqtt/console_scripts/__init__.py
nibe_mqtt/console_scripts/nibe_mqtt_service.py
nibe_mqtt-0.5.1.dist-info/LICENSE
nibe_mqtt-0.5.1.dist-info/METADATA
nibe_mqtt-0.5.1.dist-info/WHEEL
nibe_mqtt-0.5.1.dist-info/entry_points.txt
nibe_mqtt-0.5.1.dist-info/top_level.txt
nibe_mqtt-0.5.1.dist-info/zip-safe
nibe_mqtt-0.5.1.dist-info/RECORD
