Metadata-Version: 2.1
Name: nibe-mqtt
Version: 0.5.1
Summary: Nibe heatpump MQTT integration
Home-page: https://github.com/yozik04/nibe-mqtt
Author: Jevgeni Kiski
Author-email: yozik04@gmail.com
License: LGPL 3
Project-URL: Bug Tracker, https://github.com/yozik04/nibe-mqtt/issues
Keywords: nibe modbus library nibegw mqtt
Classifier: Development Status :: 1 - Planning
Classifier: Intended Audience :: Developers
Classifier: License :: OSI Approved :: GNU Lesser General Public License v3 (LGPLv3)
Classifier: Operating System :: OS Independent
Classifier: Programming Language :: Python
Classifier: Programming Language :: Python :: 3 :: Only
Classifier: Programming Language :: Python :: 3.9
Classifier: Programming Language :: Python :: 3.10
Classifier: Programming Language :: Python :: 3.11
Requires-Python: >=3.9
License-File: LICENSE
Requires-Dist: nibe <3.0.0,>=2.7.0
Requires-Dist: paho-mqtt <2.0.0,>=1.5.0
Requires-Dist: voluptuous >=0.13.0
Requires-Dist: pyyaml >=6.0
Requires-Dist: python-slugify >=6.0.0
